amoApi/API.py
amoApi/__init__.py
amoApi/amoEntities/__init__.py
amoApi/amoEntities/base.py
amoApi/amoEntities/company.py
amoApi/amoEntities/contact.py
amoApi/amoEntities/custom_field.py
amoApi/amoEntities/lead.py
amoApi/amoEntities/tag.py
amoApi/amoEntities/user.py
amoApi/serializers/__init__.py
amoApi/serializers/base_serializer.py
amoApi/serializers/contact_serializer.py
amoApi/serializers/lead_serializer.py
amoChatApi/API.py
amoChatApi/AbstractMessage.py
amoChatApi/Payload.py
amoChatApi/PhotoMessage.py
amoChatApi/TextMessage.py
amoChatApi/__init__.py
apiAmoCRM-0.3.1.dist-info/METADATA
apiAmoCRM-0.3.1.dist-info/WHEEL
apiAmoCRM-0.3.1.dist-info/top_level.txt
apiAmoCRM-0.3.1.dist-info/RECORD
