Metadata-Version: 2.1
Name: apiAmoCRM
Version: 0.3.1
Summary: Api for amoCRM
Home-page: https://github.com/cheboxarov/DialogServicesWidgets.git
Author: wlovem
Author-email: wlovemrock@gmail.com
Classifier: Programming Language :: Python :: 3
Classifier: License :: OSI Approved :: MIT License
Classifier: Operating System :: OS Independent
Requires-Python: >=3
Requires-Dist: requests
